silverpop/__init__.py
silverpop/api.py
silverpop/utils.py
silverpop/tests/__init__.py
silverpop/tests/test_utils.py
pysilverpop-0.2.6.dist-info/LICENSE
pysilverpop-0.2.6.dist-info/METADATA
pysilverpop-0.2.6.dist-info/WHEEL
pysilverpop-0.2.6.dist-info/top_level.txt
pysilverpop-0.2.6.dist-info/RECORD
