Metadata-Version: 2.1
Name: pysilverpop
Version: 0.2.6
Summary: Python wrapper for Acoustic (formerly Silverpop).
Home-page: https://github.com/theatlantic/pysilverpop
Author: The Atlantic
Author-email: programmers@theatlantic.com
License: BSD
Platform: any
Classifier: Development Status :: 5 - Production/Stable
Classifier: Intended Audience :: Developers
Classifier: Operating System :: OS Independent
Classifier: Programming Language :: Python
Classifier: Programming Language :: Python :: 2
Classifier: Programming Language :: Python :: 2.7
Classifier: Programming Language :: Python :: 3
Classifier: Programming Language :: Python :: 3.4
Classifier: Programming Language :: Python :: 3.5
Classifier: Programming Language :: Python :: 3.6
Classifier: Programming Language :: Python :: 3.7
Requires-Python: >=2.7, !=3.0.*, !=3.1.*, !=3.2.*, !=3.3.*, <4
License-File: LICENSE
Requires-Dist: six
Requires-Dist: requests
Requires-Dist: requests-oauthlib
